simple_async_command_manager/__init__.py
simple_async_command_manager/commands/__init__.py
simple_async_command_manager/commands/command_bases.py
simple_async_command_manager/commands/shared_commands.py
simple_async_command_manager/event_handlers/__init__.py
simple_async_command_manager/event_handlers/stdin_event_handler.py
simple_async_command_manager-0.1.0.dist-info/LICENSE
simple_async_command_manager-0.1.0.dist-info/METADATA
simple_async_command_manager-0.1.0.dist-info/WHEEL
simple_async_command_manager-0.1.0.dist-info/top_level.txt
simple_async_command_manager-0.1.0.dist-info/RECORD
