Metadata-Version: 2.1
Name: simple-async-command-manager
Version: 0.1.0
Summary: Simple command manager and asyncio command queue handler with wraps for subprocesses and synchronous commands. Designed to be modular for easy profiling and monitoring.
Author-email: Steven Broaddus <Steven.Broaddus220@gmail.com>
License: GNU GENERAL PUBLIC LICENSE
License-File: LICENSE
